[
    {
        "handle": "@Billahubhaisaab\n·\nJul 10, 2023",
        "text": "Update On Seedhe Maut's mixtape \"LUNCH BREAK\" ",
        "timestamp": "2025-12-18T13:06:31.024697"
    },
    {
        "handle": "@Billahubhaisaab\n·\nAug 3, 2023",
        "text": "Seedhe maut announced LUNCH BREAK track list ",
        "timestamp": "2025-12-18T13:06:31.042128"
    },
    {
        "handle": "@BetTrader429\n·\nDec 17",
        "text": " Tera bhaiii Seedhe Maut \n\n#MoodIndigo",
        "timestamp": "2025-12-18T13:06:31.061234"
    },
    {
        "handle": "@pushh_shh\n·\nJun 25, 2024",
        "text": "Seedhe Maut's biography movie was just announced!!\n\nFirst look at the poster",
        "timestamp": "2025-12-18T13:06:31.077373"
    },
    {
        "handle": "@Stanking4lyf\n·\nJan 16",
        "text": "SEEDHE MAUT DESKTOP WALLPAPER FROM SOYI NHI MV\nA THREAD ",
        "timestamp": "2025-12-18T13:06:33.630566"
    },
    {
        "handle": "@Billahubhaisaab\n·\nJul 22, 2023",
        "text": "KRSNA X SEEDHE MAUT in Lunch Break ",
        "timestamp": "2025-12-18T13:06:33.648020"
    },
    {
        "handle": "@tanishaitaan\n·\nDec 16",
        "text": "seedhe maut",
        "timestamp": "2025-12-18T13:06:35.360025"
    },
    {
        "handle": "@akkiee01\n·\nOct 29",
        "text": "Ek kadam seedhe Maut k naam",
        "timestamp": "2025-12-18T13:06:35.373684"
    },
    {
        "handle": "@shreyavrmz\n·\nNov 23",
        "text": "Men say they have good music taste and then listen to seedhe maut",
        "timestamp": "2025-12-18T13:06:38.483744"
    },
    {
        "handle": "@s7marth\n·\nJun 27, 2024",
        "text": "Seedhe Maut: Disrespecting Fans and Failing to Handle Criticism!\nA thread ",
        "timestamp": "2025-12-18T13:06:38.502109"
    },
    {
        "handle": "@wavedant_\n·\nDec 1",
        "text": "What is life without a direct death?",
        "timestamp": "2025-12-18T13:06:38.516664"
    }
]